huscy/medical_notes/__init__.py
huscy/medical_notes/apps.py
huscy/medical_notes/models.py
huscy/medical_notes/serializers.py
huscy/medical_notes/services.py
huscy/medical_notes/urls.py
huscy/medical_notes/viewsets.py
huscy/medical_notes/migrations/.gitignore
huscy/medical_notes/migrations/0001_initial.py
huscy/medical_notes/migrations/__init__.py
huscy_medical_notes-0.1.0.dist-info/METADATA
huscy_medical_notes-0.1.0.dist-info/WHEEL
huscy_medical_notes-0.1.0.dist-info/licenses/LICENSE
huscy_medical_notes-0.1.0.dist-info/RECORD
