Metadata-Version: 2.4
Name: huscy.medical_notes
Version: 0.1.0
Project-URL: homepage, https://bitbucket.org/huscy/medical_notes
Author-email: Stefan Bunde <stefanbunde+git@posteo.de>
License-Expression: AGPL-3.0-or-later
License-File: LICENSE
Classifier: Development Status :: 4 - Beta
Classifier: Framework :: Django
Classifier: Framework :: Django :: 4.2
Classifier: Framework :: Django :: 5.2
Classifier: Framework :: Django :: 6.0
Classifier: Operating System :: OS Independent
Classifier: Programming Language :: Python
Classifier: Programming Language :: Python :: 3
Classifier: Programming Language :: Python :: 3 :: Only
Classifier: Programming Language :: Python :: 3.10
Classifier: Programming Language :: Python :: 3.11
Classifier: Programming Language :: Python :: 3.12
Classifier: Programming Language :: Python :: 3.13
Classifier: Programming Language :: Python :: 3.14
Requires-Dist: huscy-subjects
Requires-Dist: huscy-users
Provides-Extra: development
Requires-Dist: psycopg2-binary; extra == 'development'
Provides-Extra: testing
Requires-Dist: tox; extra == 'testing'
Requires-Dist: watchdog; extra == 'testing'
